ittaxcode/__init__.py
ittaxcode/ittc.py
ittaxcode-0.0.1.dist-info/METADATA
ittaxcode-0.0.1.dist-info/WHEEL
ittaxcode-0.0.1.dist-info/licenses/LICENSE
ittaxcode-0.0.1.dist-info/RECORD
