Metadata-Version: 2.3
Name: ittaxcode
Version: 0.0.1
Summary: Manage Italian individual tax code
Project-URL: Homepage, https://github.com/pinuxone/ItTaxCode
Author-email: Giuseppe Latini <giuseppe.latini@gmail.com>
License-File: LICENSE
Classifier: License :: OSI Approved :: MIT License
Classifier: Operating System :: OS Independent
Classifier: Programming Language :: Python :: 3
Requires-Python: >=3.7
